CHANGELOG.rst
LICENSE
MANIFEST.in
README.rst
setup.py
xenoGI/DTLOR_DP.py
xenoGI/Family.py
xenoGI/Greedy.py
xenoGI/Island.py
xenoGI/Score.py
xenoGI/Tree.py
xenoGI/__init__.py
xenoGI/__main__.py
xenoGI/analysis.py
xenoGI/blast.py
xenoGI/families.py
xenoGI/fasta.py
xenoGI/genbank.py
xenoGI/genomes.py
xenoGI/islandBed.py
xenoGI/islands.py
xenoGI/new_DTLOR_DP.py
xenoGI/parameters.py
xenoGI/scores.py
xenoGI/trees.py
xenoGI/xenoGI.py
xenoGI.egg-info/PKG-INFO
xenoGI.egg-info/SOURCES.txt
xenoGI.egg-info/dependency_links.txt
xenoGI.egg-info/entry_points.txt
xenoGI.egg-info/requires.txt
xenoGI.egg-info/top_level.txt