Metadata-Version: 2.1
Name: xenoGI
Version: 3.1.1
Summary: Python command line application for detecting genomic island insertions in clades of microbes.
Home-page: https://github.com/ecbush/xenoGI
Author: Eliot Bush
Author-email: bush@hmc.edu
License: UNKNOWN
Platform: UNKNOWN
Classifier: Programming Language :: Python :: 3
Classifier: License :: OSI Approved :: GNU General Public License v3 (GPLv3)
Classifier: Operating System :: OS Independent
License-File: LICENSE
